minz/__init__.py
minz/models/__init__.py
minz/models/command.py
minz/util/__init__.py
minz-0.0.1.dist-info/LICENSE
minz-0.0.1.dist-info/METADATA
minz-0.0.1.dist-info/WHEEL
minz-0.0.1.dist-info/top_level.txt
minz-0.0.1.dist-info/RECORD
