Metadata-Version: 2.1
Name: minz
Version: 0.0.1
Summary: Very simple cli framework for the very lazy
Author-email: Nick Palenchar <nickpal@nickpalenchar.com>
Project-URL: Homepage, https://github.com/nickpalenchar/minz
Project-URL: Issues, https://github.com/nickpalenchar/minz/issues
Classifier: Programming Language :: Python :: 3
Classifier: License :: OSI Approved :: MIT License
Classifier: Operating System :: OS Independent
Requires-Python: >=3.10
License-File: LICENSE
